boring_math/special_functions/__init__.py
boring_math/special_functions/py.typed
boring_math_special_functions-0.1.0.dist-info/licenses/LICENSE
boring_math_special_functions-0.1.0.dist-info/WHEEL
boring_math_special_functions-0.1.0.dist-info/METADATA
boring_math_special_functions-0.1.0.dist-info/RECORD
