Metadata-Version: 2.4
Name: boring-math-special-functions
Version: 0.1.0
Summary: Mathematical special functions
Keywords: special functions,sine,exponential
Author-email: "Geoffrey R. Scheller" <geoffrey@scheller.com>
Requires-Python: >=3.13
Classifier: Development Status :: 1 - Planning
Classifier: Framework :: Pytest
Classifier: Intended Audience :: Education
Classifier: License :: OSI Approved :: Apache Software License
Classifier: Operating System :: OS Independent
Classifier: Programming Language :: Python :: 3.13
Classifier: Typing :: Typed
License-File: LICENSE
Requires-Dist: pytest>=8.4.1 ; extra == "test"
Project-URL: Changelog, https://github.com/grscheller/boring-math-special-functions/blob/main/CHANGELOG.rst
Project-URL: Documentation, https://grscheller.github.io/boring-math/special_functions/development/build/html/
Project-URL: Homepage, https://grscheller.github.io/boring-math/homepage/build/html
Project-URL: Source, https://github.com/grscheller/boring-math-special-functions
Provides-Extra: test
